csvmodel/__init__.py
csvmodel/config.py
csvmodel/csvfile.py
csvmodel/errors.py
csvmodel/main.py
csvmodel/testing.py
csvmodel/types.py
csvmodel/validator.py
csvmodel-4.dist-info/METADATA
csvmodel-4.dist-info/WHEEL
csvmodel-4.dist-info/entry_points.txt
csvmodel-4.dist-info/top_level.txt
csvmodel-4.dist-info/RECORD
