Metadata-Version: 2.1
Name: csvmodel
Version: 4
Author: Ingo Fruend
Author-email: github@ingofruend.net
Requires-Dist: docopt
Requires-Dist: jsonschema
Requires-Dist: pydantic[email]
